bytededt/__init__.py
bytededt/__version__.py
bytededt/ecom_debug_trace.py
bytededt/utils/__init__.py
bytededt/utils/metrics.py
bytededt/utils/models.py
bytededt/utils/tools.py
bytededt-0.0.5.dist-info/METADATA
bytededt-0.0.5.dist-info/WHEEL
bytededt-0.0.5.dist-info/top_level.txt
bytededt-0.0.5.dist-info/RECORD
